{
  "meta": {
    "generated_by": "generate_pandas_api_notebooks.py",
    "python_version": "3.10.19 (main, Jan 12 2026, 17:41:56) [GCC 13.3.0]",
    "pandas_version": "missing",
    "platform": "Linux-6.12.47-x86_64-with-glibc2.39",
    "target_pandas": "2.2.*",
    "target_order": [
      "DataFrame",
      "Series",
      "Index",
      "GroupBy",
      "Window",
      "TopLevel"
    ],
    "warning": "fallback inventory used (--allow-fallback enabled without pandas/numpy)"
  },
  "targets": {
    "DataFrame": [
      {
        "name": "head",
        "kind": "callable",
        "qualname": "pandas.DataFrame.head",
        "signature": null,
        "deprecated": null,
        "alias_of": null
      },
      {
        "name": "tail",
        "kind": "callable",
        "qualname": "pandas.DataFrame.tail",
        "signature": null,
        "deprecated": null,
        "alias_of": null
      },
      {
        "name": "loc",
        "kind": "indexer_accessor",
        "qualname": "pandas.DataFrame.loc",
        "signature": null,
        "deprecated": null,
        "alias_of": null
      },
      {
        "name": "iloc",
        "kind": "indexer_accessor",
        "qualname": "pandas.DataFrame.iloc",
        "signature": null,
        "deprecated": null,
        "alias_of": null
      },
      {
        "name": "at",
        "kind": "indexer_accessor",
        "qualname": "pandas.DataFrame.at",
        "signature": null,
        "deprecated": null,
        "alias_of": null
      },
      {
        "name": "iat",
        "kind": "indexer_accessor",
        "qualname": "pandas.DataFrame.iat",
        "signature": null,
        "deprecated": null,
        "alias_of": null
      },
      {
        "name": "merge",
        "kind": "callable",
        "qualname": "pandas.DataFrame.merge",
        "signature": null,
        "deprecated": null,
        "alias_of": null
      },
      {
        "name": "groupby",
        "kind": "callable",
        "qualname": "pandas.DataFrame.groupby",
        "signature": null,
        "deprecated": null,
        "alias_of": null
      },
      {
        "name": "assign",
        "kind": "callable",
        "qualname": "pandas.DataFrame.assign",
        "signature": null,
        "deprecated": null,
        "alias_of": null
      },
      {
        "name": "dropna",
        "kind": "callable",
        "qualname": "pandas.DataFrame.dropna",
        "signature": null,
        "deprecated": null,
        "alias_of": null
      },
      {
        "name": "fillna",
        "kind": "callable",
        "qualname": "pandas.DataFrame.fillna",
        "signature": null,
        "deprecated": null,
        "alias_of": null
      }
    ],
    "Series": [
      {
        "name": "head",
        "kind": "callable",
        "qualname": "pandas.Series.head",
        "signature": null,
        "deprecated": null,
        "alias_of": null
      },
      {
        "name": "tail",
        "kind": "callable",
        "qualname": "pandas.Series.tail",
        "signature": null,
        "deprecated": null,
        "alias_of": null
      },
      {
        "name": "loc",
        "kind": "indexer_accessor",
        "qualname": "pandas.Series.loc",
        "signature": null,
        "deprecated": null,
        "alias_of": null
      },
      {
        "name": "iloc",
        "kind": "indexer_accessor",
        "qualname": "pandas.Series.iloc",
        "signature": null,
        "deprecated": null,
        "alias_of": null
      },
      {
        "name": "at",
        "kind": "indexer_accessor",
        "qualname": "pandas.Series.at",
        "signature": null,
        "deprecated": null,
        "alias_of": null
      },
      {
        "name": "iat",
        "kind": "indexer_accessor",
        "qualname": "pandas.Series.iat",
        "signature": null,
        "deprecated": null,
        "alias_of": null
      },
      {
        "name": "str",
        "kind": "indexer_accessor",
        "qualname": "pandas.Series.str",
        "signature": null,
        "deprecated": null,
        "alias_of": null
      },
      {
        "name": "dt",
        "kind": "indexer_accessor",
        "qualname": "pandas.Series.dt",
        "signature": null,
        "deprecated": null,
        "alias_of": null
      },
      {
        "name": "cat",
        "kind": "indexer_accessor",
        "qualname": "pandas.Series.cat",
        "signature": null,
        "deprecated": null,
        "alias_of": null
      },
      {
        "name": "astype",
        "kind": "callable",
        "qualname": "pandas.Series.astype",
        "signature": null,
        "deprecated": null,
        "alias_of": null
      },
      {
        "name": "value_counts",
        "kind": "callable",
        "qualname": "pandas.Series.value_counts",
        "signature": null,
        "deprecated": null,
        "alias_of": null
      }
    ],
    "Index": [
      {
        "name": "astype",
        "kind": "callable",
        "qualname": "pandas.Index.astype",
        "signature": null,
        "deprecated": null,
        "alias_of": null
      },
      {
        "name": "isin",
        "kind": "callable",
        "qualname": "pandas.Index.isin",
        "signature": null,
        "deprecated": null,
        "alias_of": null
      },
      {
        "name": "min",
        "kind": "callable",
        "qualname": "pandas.Index.min",
        "signature": null,
        "deprecated": null,
        "alias_of": null
      },
      {
        "name": "max",
        "kind": "callable",
        "qualname": "pandas.Index.max",
        "signature": null,
        "deprecated": null,
        "alias_of": null
      },
      {
        "name": "take",
        "kind": "callable",
        "qualname": "pandas.Index.take",
        "signature": null,
        "deprecated": null,
        "alias_of": null
      }
    ],
    "GroupBy": [
      {
        "name": "sum",
        "kind": "callable",
        "qualname": "pandas.core.groupby.generic.DataFrameGroupBy.sum",
        "signature": null,
        "deprecated": null,
        "alias_of": null
      },
      {
        "name": "mean",
        "kind": "callable",
        "qualname": "pandas.core.groupby.generic.DataFrameGroupBy.mean",
        "signature": null,
        "deprecated": null,
        "alias_of": null
      },
      {
        "name": "count",
        "kind": "callable",
        "qualname": "pandas.core.groupby.generic.DataFrameGroupBy.count",
        "signature": null,
        "deprecated": null,
        "alias_of": null
      },
      {
        "name": "agg",
        "kind": "callable",
        "qualname": "pandas.core.groupby.generic.DataFrameGroupBy.agg",
        "signature": null,
        "deprecated": null,
        "alias_of": null
      },
      {
        "name": "apply",
        "kind": "callable",
        "qualname": "pandas.core.groupby.generic.DataFrameGroupBy.apply",
        "signature": null,
        "deprecated": null,
        "alias_of": null
      },
      {
        "name": "transform",
        "kind": "callable",
        "qualname": "pandas.core.groupby.generic.DataFrameGroupBy.transform",
        "signature": null,
        "deprecated": null,
        "alias_of": null
      }
    ],
    "Window": [
      {
        "name": "sum",
        "kind": "callable",
        "qualname": "pandas.core.window.rolling.Rolling.sum",
        "signature": null,
        "deprecated": null,
        "alias_of": null
      },
      {
        "name": "mean",
        "kind": "callable",
        "qualname": "pandas.core.window.rolling.Rolling.mean",
        "signature": null,
        "deprecated": null,
        "alias_of": null
      },
      {
        "name": "std",
        "kind": "callable",
        "qualname": "pandas.core.window.rolling.Rolling.std",
        "signature": null,
        "deprecated": null,
        "alias_of": null
      },
      {
        "name": "var",
        "kind": "callable",
        "qualname": "pandas.core.window.rolling.Rolling.var",
        "signature": null,
        "deprecated": null,
        "alias_of": null
      },
      {
        "name": "min",
        "kind": "callable",
        "qualname": "pandas.core.window.rolling.Rolling.min",
        "signature": null,
        "deprecated": null,
        "alias_of": null
      },
      {
        "name": "max",
        "kind": "callable",
        "qualname": "pandas.core.window.rolling.Rolling.max",
        "signature": null,
        "deprecated": null,
        "alias_of": null
      },
      {
        "name": "count",
        "kind": "callable",
        "qualname": "pandas.core.window.rolling.Rolling.count",
        "signature": null,
        "deprecated": null,
        "alias_of": null
      }
    ],
    "TopLevel": [
      {
        "name": "concat",
        "kind": "callable",
        "qualname": "pandas.concat",
        "signature": null,
        "deprecated": null,
        "alias_of": null
      },
      {
        "name": "merge",
        "kind": "callable",
        "qualname": "pandas.merge",
        "signature": null,
        "deprecated": null,
        "alias_of": null
      },
      {
        "name": "pivot_table",
        "kind": "callable",
        "qualname": "pandas.pivot_table",
        "signature": null,
        "deprecated": null,
        "alias_of": null
      },
      {
        "name": "date_range",
        "kind": "callable",
        "qualname": "pandas.date_range",
        "signature": null,
        "deprecated": null,
        "alias_of": null
      },
      {
        "name": "to_datetime",
        "kind": "callable",
        "qualname": "pandas.to_datetime",
        "signature": null,
        "deprecated": null,
        "alias_of": null
      },
      {
        "name": "to_timedelta",
        "kind": "callable",
        "qualname": "pandas.to_timedelta",
        "signature": null,
        "deprecated": null,
        "alias_of": null
      },
      {
        "name": "read_csv",
        "kind": "callable",
        "qualname": "pandas.read_csv",
        "signature": null,
        "deprecated": null,
        "alias_of": null
      }
    ]
  }
}